incuna_test_utils/__init__.py
incuna_test_utils/compat.py
incuna_test_utils/utils.py
incuna_test_utils/factories/__init__.py
incuna_test_utils/factories/feincms_page.py
incuna_test_utils/factories/images.py
incuna_test_utils/factories/user.py
incuna_test_utils/factories/files/__init__.py
incuna_test_utils/factories/files/image.png
incuna_test_utils/management/__init__.py
incuna_test_utils/management/commands/__init__.py
incuna_test_utils/management/commands/check_migrations.py
incuna_test_utils/testcases/__init__.py
incuna_test_utils/testcases/api_examples.py
incuna_test_utils/testcases/api_request.py
incuna_test_utils/testcases/integration.py
incuna_test_utils/testcases/request.py
incuna_test_utils/testcases/urls.py
tests/complete_migrations/__init__.py
tests/complete_migrations/models.py
tests/complete_migrations/migrations/0001_initial.py
tests/complete_migrations/migrations/__init__.py
tests/factory_tests/__init__.py
tests/factory_tests/test_feincms_page.py
tests/factory_tests/test_images.py
tests/factory_tests/test_user.py
tests/partial_migrations/__init__.py
tests/partial_migrations/models.py
tests/partial_migrations/migrations/0001_initial.py
tests/partial_migrations/migrations/__init__.py
tests/testcases/__init__.py
tests/testcases/test_admin_request.py
tests/testcases/test_api_examples.py
tests/testcases/test_api_request.py
tests/testcases/test_integration.py
tests/testcases/test_request.py
tests/testcases/test_urls.py
incuna_test_utils-8.0.0.dist-info/LICENSE
incuna_test_utils-8.0.0.dist-info/METADATA
incuna_test_utils-8.0.0.dist-info/WHEEL
incuna_test_utils-8.0.0.dist-info/top_level.txt
incuna_test_utils-8.0.0.dist-info/RECORD
