Metadata-Version: 2.1
Name: incuna-test-utils
Version: 8.0.0
Summary: Custom TestCases and other test helpers for Django apps
Home-page: https://github.com/incuna/incuna-test-utils/
Author: Incuna
Author-email: admin@incuna.com
License: BSD
Platform: UNKNOWN
Classifier: Development Status :: 5 - Production/Stable
Classifier: Framework :: Django
Classifier: Intended Audience :: Developers
Classifier: License :: OSI Approved :: BSD License
Classifier: Natural Language :: English
Classifier: Programming Language :: Python :: 2.7
Classifier: Programming Language :: Python :: 3.4
Classifier: Topic :: Software Development :: Testing
Provides-Extra: images
Requires-Dist: Pillow ; extra == 'images'
